topsis_pkg/__init__.py
topsis_pkg/topsis.py
topsis_sarthak_102303497-1.0.0.dist-info/licenses/LICENSE
topsis_sarthak_102303497-1.0.0.dist-info/METADATA
topsis_sarthak_102303497-1.0.0.dist-info/WHEEL
topsis_sarthak_102303497-1.0.0.dist-info/entry_points.txt
topsis_sarthak_102303497-1.0.0.dist-info/top_level.txt
topsis_sarthak_102303497-1.0.0.dist-info/RECORD
