Metadata-Version: 2.4
Name: Topsis-Sarthak-102303497
Version: 1.0.0
Summary: A Python package for TOPSIS multi-criteria decision analysis
Home-page: https://github.com/yourusername/Topsis-Sarthak-102203628
Author: Sarthak Gaba
Author-email: your.email@example.com
Classifier: Programming Language :: Python :: 3
Classifier: License :: OSI Approved :: MIT License
Classifier: Operating System :: OS Independent
Requires-Python: >=3.6
License-File: LICENSE
Requires-Dist: numpy
Requires-Dist: pandas
Dynamic: author
Dynamic: author-email
Dynamic: classifier
Dynamic: description
Dynamic: description-content-type
Dynamic: home-page
Dynamic: license-file
Dynamic: requires-dist
Dynamic: requires-python
Dynamic: summary
